Metadata-Version: 2.4
Name: re-cdp-patches
Version: 0.9.1
Summary: Patching CDP (Chrome DevTools Protocol) leaks on OS level. Easy to use with Playwright/Patchright.
Home-page: https://github.com/imamousenotacat/re-cdp-patches/
Author: Vinyzu, Kaliiiiiiiiii (slightly modified by imamousenotacat)
License: GNU General Public License v3.0
Keywords: re-patchright,re-browser-use,playwright,automation,fingerprints,fingerprinting,dataset,data,chrome,patching,web-automation
Classifier: Topic :: Scientific/Engineering
Classifier: Topic :: Scientific/Engineering :: Artificial Intelligence
Classifier: Topic :: Software Development
Classifier: Topic :: Software Development :: Libraries
Classifier: Topic :: Software Development :: Libraries :: Python Modules
Classifier: Topic :: Internet :: WWW/HTTP :: Browsers
Classifier: License :: OSI Approved :: Apache Software License
Classifier: Programming Language :: Python :: 3
Requires-Python: >=3.8
License-File: LICENSE
Requires-Dist: numpy
Requires-Dist: websockets
Requires-Dist: requests
Requires-Dist: pywinauto; platform_system == "Windows"
Requires-Dist: python-xlib; platform_system == "Linux"
Provides-Extra: automation-linting
Requires-Dist: playwright; extra == "automation-linting"
Requires-Dist: re-patchright; extra == "automation-linting"
Provides-Extra: testing
Requires-Dist: pytest; extra == "testing"
Requires-Dist: mypy; extra == "testing"
Requires-Dist: flake8; extra == "testing"
Requires-Dist: tox; extra == "testing"
Requires-Dist: types-requests; extra == "testing"
Requires-Dist: playwright; extra == "testing"
Requires-Dist: re-patchright; extra == "testing"
Dynamic: license-file
